bdd_tester/__init__.py
bdd_tester/core.py
bdd_tester/exceptions.py
bdd_tester/utils.py
bdd_tester-0.0.8.data/scripts/bdd_tester
tests/__init__.py
tests/test_basic.py
bdd_tester-0.0.8.dist-info/LICENSE
bdd_tester-0.0.8.dist-info/METADATA
bdd_tester-0.0.8.dist-info/WHEEL
bdd_tester-0.0.8.dist-info/top_level.txt
bdd_tester-0.0.8.dist-info/RECORD
