Metadata-Version: 2.1
Name: bdd-tester
Version: 0.0.8
Summary: A very very basic BDD test runner
Home-page: UNKNOWN
Author: Andy Lulham
Author-email: a.lulham@gmail.com
License: MIT
Platform: UNKNOWN
Requires-Dist: gherkin-official
Requires-Dist: six
Provides-Extra: test
Requires-Dist: coveralls ; extra == 'test'
Requires-Dist: pytest ; extra == 'test'
Requires-Dist: pytest-cov ; extra == 'test'
